{"name":"Scrollfloater","tagline":"","body":"# ScrollFloater jQuery Plugin\r\n\r\n## Demo\r\nComing Soon!\r\n\r\n## Features\r\n* You can be fixed to one element in the page.\r\n* You can not apply it against several elements. The reason is that one element is fixed once the process for fixing the other elements because not work well.\r\n\r\n* ページ内の一つの要素を、スクロールに応じて最上部に固定することができる。\r\n* 複数の要素への対応を検討しているが、使い方が限定されるため現状は１つの要素のみ適応できる仕様にしてある。\r\n\r\n## Example\r\n```\r\n$('#hoge').scrollFloater();\r\n```\r\n\r\n## Licence\r\n\r\nReleased under the [MIT license](http://opensource.org/licenses/MIT)","google":"","note":"Don't delete this file! It's used internally to help with page regeneration."}